aiida_pseudo/__init__.py
aiida_pseudo/cli/__init__.py
aiida_pseudo/cli/family.py
aiida_pseudo/cli/install.py
aiida_pseudo/cli/list.py
aiida_pseudo/cli/root.py
aiida_pseudo/cli/utils.py
aiida_pseudo/cli/params/__init__.py
aiida_pseudo/cli/params/arguments.py
aiida_pseudo/cli/params/options.py
aiida_pseudo/cli/params/types.py
aiida_pseudo/common/__init__.py
aiida_pseudo/common/units.py
aiida_pseudo/data/__init__.py
aiida_pseudo/data/pseudo/__init__.py
aiida_pseudo/data/pseudo/jthxml.py
aiida_pseudo/data/pseudo/pseudo.py
aiida_pseudo/data/pseudo/psf.py
aiida_pseudo/data/pseudo/psml.py
aiida_pseudo/data/pseudo/psp8.py
aiida_pseudo/data/pseudo/upf.py
aiida_pseudo/data/pseudo/vps.py
aiida_pseudo/groups/__init__.py
aiida_pseudo/groups/family/__init__.py
aiida_pseudo/groups/family/cutoffs.py
aiida_pseudo/groups/family/pseudo.py
aiida_pseudo/groups/family/pseudo_dojo.py
aiida_pseudo/groups/family/sssp.py
aiida_pseudo/groups/mixins/__init__.py
aiida_pseudo/groups/mixins/cutoffs.py
aiida_pseudo-1.7.2.dist-info/entry_points.txt
aiida_pseudo-1.7.2.dist-info/licenses/LICENSE.txt
aiida_pseudo-1.7.2.dist-info/WHEEL
aiida_pseudo-1.7.2.dist-info/METADATA
aiida_pseudo-1.7.2.dist-info/RECORD
