Metadata-Version: 2.4
Name: aiida-pseudo
Version: 1.7.2
Summary: AiiDA plugin that simplifies working with pseudo potentials.
Keywords: aiida,pseudopotentials
Author-email: "Sebastiaan P. Huber" <mail@sphuber.net>
Requires-Python: >=3.9
Classifier: Development Status :: 5 - Production/Stable
Classifier: Framework :: AiiDA
Classifier: License :: OSI Approved :: MIT License
Classifier: Operating System :: POSIX :: Linux
Classifier: Operating System :: MacOS :: MacOS X
Classifier: Programming Language :: Python
Classifier: Programming Language :: Python :: 3.9
Classifier: Programming Language :: Python :: 3.10
Classifier: Programming Language :: Python :: 3.11
Classifier: Programming Language :: Python :: 3.12
Classifier: Programming Language :: Python :: 3.13
License-File: LICENSE.txt
Requires-Dist: aiida-core~=2.6
Requires-Dist: click~=8.0,<8.2
Requires-Dist: pint>=0.23.0,<0.25.0
Requires-Dist: requests~=2.20
Requires-Dist: pre-commit~=2.2 ; extra == "dev"
Requires-Dist: pytest>=6.0 ; extra == "dev"
Requires-Dist: sphinx~=6.0 ; extra == "docs"
Requires-Dist: sphinx-copybutton~=0.5.0 ; extra == "docs"
Requires-Dist: sphinx-book-theme~=1.0 ; extra == "docs"
Requires-Dist: sphinx-autoapi~=3.3.3 ; extra == "docs"
Requires-Dist: sphinx-click~=4.0 ; extra == "docs"
Project-URL: Documentation, https://aiida-pseudo.readthedocs.io
Project-URL: Home, https://github.com/aiidateam/aiida-pseudo
Project-URL: Source, https://github.com/aiidateam/aiida-pseudo
Provides-Extra: dev
Provides-Extra: docs
